[
    {
        "Author": "Minmoose, Asgard and Contributors",
        "Name": "Brio",
        "Punchline": "Enhanced GPosing.",
        "Description": "Control & edit actors during GPose sessions.",
        "InternalName": "Brio",
        "AssemblyVersion": "0.5.0.2",
        "TestingAssemblyVersion": "0.5.0.2",
        "RepoUrl": "https://github.com/Etheirys/Brio",
        "ApplicableVersion": "any",
        "DalamudApiLevel": 11,
        "DownloadLinkInstall": "https://github.com/Etheirys/Brio/releases/download/v0.5.0.2/Brio.zip",
        "DownloadLinkTesting": "https://github.com/Etheirys/Brio/releases/download/v0.5.0.2/Brio.zip",
        "DownloadLinkUpdate": "https://github.com/Etheirys/Brio/releases/download/v0.5.0.2/Brio.zip",
        "IconUrl": "https://raw.githubusercontent.com/Etheirys/Brio/main/Resources/Images/BrioIcon.png",
        "Tags": [ 
            "gpose",
            "brio",
            "posing",
            "pose",
            "animation",
            "xat",
            "cutscene"
        ]
    }
]
